tetraview/__init__.py
tetraview/main.py
tetraview/backend/__init__.py
tetraview/gui/__init__.py
tetraview/gui/colormap_bar.py
tetraview/gui/main_window.py
tetraview/gui/menu_bar.py
tetraview/gui/volume_display.py
tetraview/gui/volume_info.py
tetraview/gui/volume_selector.py
tetraview/utils/__init__.py
tetraview-0.1.0.dist-info/LICENSE
tetraview-0.1.0.dist-info/METADATA
tetraview-0.1.0.dist-info/WHEEL
tetraview-0.1.0.dist-info/entry_points.txt
tetraview-0.1.0.dist-info/top_level.txt
tetraview-0.1.0.dist-info/RECORD
