Metadata-Version: 2.2
Name: tetraview
Version: 0.1.0
Summary: tetraview - Interactive tomography visualization GUI
Author-email: Henri Payno <henri.payno@esrf.fr>, Pierre Paleo <pierre.paleo@esrf.fr>, Pierre-Olivier Autran <pierre-olivier.autran@esrf.fr>, Jibril Mammeri <jibril.mammeri@esrf.fr>, Jérôme Lesaint <jerome.lesaint@esrf.fr>
License: MIT License
Keywords: tomography,reconstruction,X-ray imaging,GUI,Qt,Nabu,interactive,synchrotron
Classifier: Development Status :: 3 - Alpha
Classifier: Intended Audience :: Developers
Classifier: Intended Audience :: Science/Research
Classifier: Programming Language :: Python :: 3
Classifier: Programming Language :: Python :: 3.8
Classifier: Programming Language :: Python :: 3.9
Classifier: Programming Language :: Python :: 3.10
Classifier: Programming Language :: Python :: 3.11
Classifier: Programming Language :: Python :: 3.12
Classifier: Environment :: X11 Applications :: Qt
Classifier: License :: OSI Approved :: MIT License
Classifier: Operating System :: OS Independent
Classifier: Topic :: Scientific/Engineering :: Physics
Classifier: Topic :: Scientific/Engineering :: Visualization
Requires-Python: >=3.8
License-File: LICENSE
Requires-Dist: silx
Provides-Extra: dev
Requires-Dist: isort>=5.12.0; extra == "dev"
Requires-Dist: flake8>=6.0.0; extra == "dev"
Requires-Dist: black>=23.3.0; extra == "dev"
Requires-Dist: sphinx>=7.0.0; extra == "dev"
Requires-Dist: pytest>=7.4.0; extra == "dev"
Requires-Dist: sphinx-rtd-theme; extra == "dev"
Provides-Extra: doc
Requires-Dist: sphinx; extra == "doc"
Requires-Dist: sphinx-rtd-theme; extra == "doc"
